sqlalchemy_postgresql_audit/__init__.py
sqlalchemy_postgresql_audit/ddl.py
sqlalchemy_postgresql_audit/dialect.py
sqlalchemy_postgresql_audit/install.py
sqlalchemy_postgresql_audit/plugin.py
sqlalchemy_postgresql_audit/session.py
sqlalchemy_postgresql_audit/event_listeners/__init__.py
sqlalchemy_postgresql_audit/event_listeners/alembic.py
sqlalchemy_postgresql_audit/event_listeners/sqlalchemy.py
sqlalchemy_postgresql_audit/templates/__init__.py
sqlalchemy_postgresql_audit-0.5.2.dist-info/METADATA
sqlalchemy_postgresql_audit-0.5.2.dist-info/RECORD
sqlalchemy_postgresql_audit-0.5.2.dist-info/WHEEL
sqlalchemy_postgresql_audit-0.5.2.dist-info/entry_points.txt
sqlalchemy_postgresql_audit-0.5.2.dist-info/top_level.txt
