Metadata-Version: 2.1
Name: sqlalchemy-postgresql-audit
Version: 0.5.2
Summary: A postgres audit table implementation that works with sqlalchemy and alembic
Home-page: https://github.com/huntcsg/sqlalchemy-postgresql-audit
Author: Hunter Senft-Grupp
Author-email: huntcsg@gmail.com
License: MIT
Keywords: sqlalchemy sql postgresql postgres alembic audit changelog
Platform: UNKNOWN
Classifier: Development Status :: 3 - Alpha
Classifier: Environment :: Console
Classifier: Intended Audience :: Developers
Classifier: Intended Audience :: System Administrators
Classifier: Programming Language :: Python :: 3.4
Classifier: Programming Language :: Python :: 3.5
Classifier: Programming Language :: Python :: 3.6
Classifier: Programming Language :: Python :: 3.7
Requires-Python: >=2.7,!=3.0.*,!=3.1.*,!=3.2.*,!=3.3.*
Provides-Extra: dev
Provides-Extra: docs
Provides-Extra: testing
Provides-Extra: linting
Requires-Dist: sqlalchemy
Provides-Extra: dev
Requires-Dist: tox; extra == 'dev'
Requires-Dist: pip-tools; extra == 'dev'
Provides-Extra: docs
Requires-Dist: sphinx; extra == 'docs'
Requires-Dist: sphinx-rtd-theme; extra == 'docs'
Requires-Dist: alembic; extra == 'docs'
Provides-Extra: linting
Requires-Dist: isort; extra == 'linting'
Requires-Dist: black; extra == 'linting'
Requires-Dist: flake8; extra == 'linting'
Provides-Extra: testing
Requires-Dist: pytest; extra == 'testing'
Requires-Dist: pytest-cov; extra == 'testing'
Requires-Dist: psycopg2-binary; extra == 'testing'
Provides-Extra: testing
Requires-Dist: mock; (python_version < "3") and extra == 'testing'
